audio_feeder/__init__.py
audio_feeder/_compat.py
audio_feeder/_db_types.py
audio_feeder/_object_types.py
audio_feeder/_useful_types.py
audio_feeder/_version.py
audio_feeder/app.py
audio_feeder/cache_utils.py
audio_feeder/cli.py
audio_feeder/config.py
audio_feeder/database_handler.py
audio_feeder/directory_parser.py
audio_feeder/file_location.py
audio_feeder/file_probe.py
audio_feeder/hash_utils.py
audio_feeder/html_utils.py
audio_feeder/m4btools.py
audio_feeder/media_renderer.py
audio_feeder/metadata_loader.py
audio_feeder/object_handler.py
audio_feeder/page_generator.py
audio_feeder/pages.py
audio_feeder/resolver.py
audio_feeder/resources.py
audio_feeder/rss_feeds.py
audio_feeder/segmenter.py
audio_feeder/sql_database_handler.py
audio_feeder/updater.py
audio_feeder/yaml_database_handler.py
audio_feeder/data/__init__.py
audio_feeder/data/css/__init__.py
audio_feeder/data/css/fontawesome-subset.css
audio_feeder/data/css/main.css
audio_feeder/data/site/__init__.py
audio_feeder/data/site/fonts/__init__.py
audio_feeder/data/site/fonts/fontawesome-subset.woff
audio_feeder/data/site/fonts/fontawesome-subset.woff2
audio_feeder/data/site/site-images/__init__.py
audio_feeder/data/site/site-images/default_cover.svg
audio_feeder/data/templates/__init__.py
audio_feeder/data/templates/entry_types/__init__.py
audio_feeder/data/templates/entry_types/Book/__init__.py
audio_feeder/data/templates/entry_types/Book/author.tpl
audio_feeder/data/templates/entry_types/Book/description.tpl
audio_feeder/data/templates/entry_types/Book/name.tpl
audio_feeder/data/templates/pages/__init__.py
audio_feeder/data/templates/pages/list.tpl
audio_feeder/data/templates/rss/__init__.py
audio_feeder/data/templates/rss/rss_feed.tpl
audio_feeder/data/templates/rss/entry_types/__init__.py
audio_feeder/data/templates/rss/entry_types/Book/__init__.py
audio_feeder/data/templates/rss/entry_types/Book/author.tpl
audio_feeder/data/templates/rss/entry_types/Book/description.tpl
audio_feeder-0.6.2.dist-info/LICENSE
audio_feeder-0.6.2.dist-info/METADATA
audio_feeder-0.6.2.dist-info/WHEEL
audio_feeder-0.6.2.dist-info/entry_points.txt
audio_feeder-0.6.2.dist-info/top_level.txt
audio_feeder-0.6.2.dist-info/RECORD
