Metadata-Version: 2.1
Name: audio-feeder
Version: 0.6.2
Summary: audio-feeder provides a server that serves your audiobooks and other audio
Author: Paul Ganssle
License: Apache 2.0
Classifier: Development Status :: 1 - Planning
Classifier: Intended Audience :: Developers
Classifier: Framework :: Flask
Classifier: License :: OSI Approved :: Apache Software License
Classifier: Programming Language :: Python
Classifier: Programming Language :: Python :: 3 :: Only
Classifier: Programming Language :: Python :: 3
Classifier: Programming Language :: Python :: 3.9
Classifier: Programming Language :: Python :: 3.10
Classifier: Programming Language :: Python :: 3.11
Requires-Python: >=3.9
License-File: LICENSE
Requires-Dist: Flask (>=0.11.1)
Requires-Dist: pyyaml (>=6.0)
Requires-Dist: qrcode (>=5.3)
Requires-Dist: Pillow (>=3.4.2)
Requires-Dist: requests (>=2.12.4)
Requires-Dist: jinja2
Requires-Dist: click (>=6.0)
Requires-Dist: progressbar2
Requires-Dist: lxml (>=2.0)
Requires-Dist: SQLAlchemy (>=1.4)
Requires-Dist: attrs (>=22.0)
Requires-Dist: backports.strenum (>=1.1.1) ; python_version < "3.11"
Requires-Dist: typing-extensions (>=4.0.0) ; python_version < "3.11"
